README.rst
pytest_vw.py
setup.py
pytest_vw.egg-info/PKG-INFO
pytest_vw.egg-info/SOURCES.txt
pytest_vw.egg-info/dependency_links.txt
pytest_vw.egg-info/entry_points.txt
pytest_vw.egg-info/requires.txt
pytest_vw.egg-info/top_level.txt