Metadata-Version: 1.1
Name: pytest-vw
Version: 0.1.0
Summary: pytest-vw makes your failing test cases succeed under CI tools scrutiny
Home-page: https://github.com/The-Compiler/pytest-vw
Author: Florian Bruhin
Author-email: me@the-compiler.org
License: MIT
Platform: UNKNOWN
Classifier: Development Status :: 4 - Beta
Classifier: Intended Audience :: Developers
Classifier: Topic :: Software Development :: Testing
Classifier: Programming Language :: Python
Classifier: Operating System :: OS Independent
Classifier: License :: OSI Approved :: MIT License
